bplusplus/__init__.py
bplusplus/collect.py
bplusplus/inference.py
bplusplus/insect_detector.py
bplusplus/prepare.py
bplusplus/tracker.py
bplusplus/train.py
bplusplus/validation.py
bplusplus-2.0.0.dist-info/LICENSE
bplusplus-2.0.0.dist-info/METADATA
bplusplus-2.0.0.dist-info/WHEEL
bplusplus-2.0.0.dist-info/RECORD
