Metadata-Version: 2.3
Name: bplusplus
Version: 2.0.0
Summary: A simple method to create AI models for biodiversity, with collect and prepare pipeline
License: MIT
Author: Titus Venverloo
Author-email: tvenver@mit.edu
Requires-Python: >=3.10,<4.0
Classifier: License :: OSI Approved :: MIT License
Classifier: Programming Language :: Python :: 3
Classifier: Programming Language :: Python :: 3.10
Classifier: Programming Language :: Python :: 3.11
Classifier: Programming Language :: Python :: 3.12
Classifier: Programming Language :: Python :: 3.13
Requires-Dist: numpy (>=1.26.0,<1.26.5) ; sys_platform == "win32"
Requires-Dist: numpy (>=1.26.0,<1.27.0) ; sys_platform == "darwin" and platform_machine == "arm64"
Requires-Dist: numpy (>=1.26.0,<1.27.0) ; sys_platform == "darwin" and platform_machine == "x86_64"
Requires-Dist: numpy (>=1.26.0,<1.27.0) ; sys_platform == "linux" and platform_machine == "aarch64"
Requires-Dist: numpy (>=1.26.0,<1.27.0) ; sys_platform == "linux" and platform_machine == "x86_64"
Requires-Dist: pandas (==2.1.4)
Requires-Dist: pillow (>=10.0.0,<12.0.0) ; sys_platform == "darwin"
Requires-Dist: pillow (>=10.0.0,<12.0.0) ; sys_platform == "linux"
Requires-Dist: pillow (>=10.0.0,<12.0.0) ; sys_platform == "win32"
Requires-Dist: prettytable (==3.7.0)
Requires-Dist: pygbif (==0.6.5)
Requires-Dist: pyyaml (==6.0.1)
Requires-Dist: requests (==2.25.1)
Requires-Dist: scikit-learn (>=1.3.0,<1.7.0) ; sys_platform == "linux" and platform_machine == "aarch64"
Requires-Dist: scikit-learn (>=1.3.0,<1.7.0) ; sys_platform == "win32"
Requires-Dist: scikit-learn (>=1.4.0,<1.8.0) ; sys_platform == "darwin" and platform_machine == "arm64"
Requires-Dist: scikit-learn (>=1.4.0,<1.8.0) ; sys_platform == "darwin" and platform_machine == "x86_64"
Requires-Dist: scikit-learn (>=1.4.0,<1.8.0) ; sys_platform == "linux" and platform_machine == "x86_64"
Requires-Dist: tabulate (==0.9.0)
Requires-Dist: torch (>=2.0.0,<2.8.0) ; sys_platform == "darwin" and platform_machine == "arm64"
Requires-Dist: torch (>=2.0.0,<2.8.0) ; sys_platform == "linux"
Requires-Dist: torch (>=2.0.0,<2.8.0) ; sys_platform == "win32"
Requires-Dist: torch (>=2.2.0,<2.3.0) ; sys_platform == "darwin" and platform_machine == "x86_64"
Requires-Dist: tqdm (==4.66.4)
Requires-Dist: ultralytics (==8.3.173)
Requires-Dist: validators (==0.33.0)
